hsuanwu/__init__.py
hsuanwu/common/__init__.py
hsuanwu/common/logger.py
hsuanwu/common/typing.py
hsuanwu/envs/dmc/__init__.py
hsuanwu/envs/dmc/natural_imgsource.py
hsuanwu/envs/dmc/wrappers.py
hsuanwu/xploit/__init__.py
hsuanwu/xploit/utils.py
hsuanwu/xploit/encoder/base.py
hsuanwu/xploit/encoder/cnn_encoders.py
hsuanwu/xploit/encoder/mlp_encoders.py
hsuanwu/xploit/learner/drqv2.py
hsuanwu/xploit/learner/ppg.py
hsuanwu/xploit/storage/nstep_replay_buffer.py
hsuanwu/xploit/storage/prioritized_replay_buffer.py
hsuanwu/xploit/storage/vanilla_replay_buffer.py
hsuanwu/xplore/__init__.py
hsuanwu/xplore/augmentation/random_shift.py
hsuanwu/xplore/noise/truncated_normal.py
hsuanwu/xplore/reward/__init__.py
hsuanwu/xplore/reward/base.py
hsuanwu/xplore/reward/re3.py
hsuanwu-0.0.1.dist-info/METADATA
hsuanwu-0.0.1.dist-info/WHEEL
hsuanwu-0.0.1.dist-info/licenses/LICENSE
hsuanwu-0.0.1.dist-info/RECORD
