Metadata-Version: 2.1
Name: hsuanwu
Version: 0.0.1
Summary: Long-Term Evolution Project of Reinforcement Learning
Project-URL: Homepage, https://github.com/BellmanProject/Hsuanwu
Project-URL: Bug Tracker, https://github.com/BellmanProject/Hsuanwu/issues
Author-email: Bellman Project <friedrichyuan19990827@gmail.com>
License-File: LICENSE
Classifier: License :: OSI Approved :: MIT License
Classifier: Operating System :: OS Independent
Classifier: Programming Language :: Python :: 3
Requires-Python: >=3.8
